alu32.v
module alu32(sum,a,b,zout,gin,status);//ALU operation according to the ALU control line values
output [31:0] sum;
input [31:0] a,b; 
input [2:0] gin;//ALU control line
reg [31:0] sum;
reg [31:0] less;
output zout;
reg zout;
output reg [2:0] status; // 210=>nzv
always @(a or b or gin)
begin
status = 3'b000; // Initialize status
	case(gin)
	3'b010: begin // ALU control line = 010, ADD
           sum = a + b;
            if ((a[31] == b[31]) && (sum[31] != a[31])) // Overflow check
                status[0] = 1'b1;
      end

	3'b110: begin // ALU control line = 110, SUB
            sum=a+1+(~b);
            if ((a[31] != b[31]) && (sum[31] != a[31])) // Overflow check
                status[0] = 1'b1;
      end
	3'b111: begin // ALU control line = 111, SLT
           less=a+1+(~b);
            if (less[31])
                sum = 32'b1;
            if ((a[31] != b[31]) && (less[31] != a[31])) // Overflow check
                status[0] = 1'b1;
      end
	3'b000: sum=a & b;	//ALU control line=000, AND
	3'b001: sum=a|b;		//ALU control line=001, OR
	default: sum=31'bx;	
	endcase
zout=~(|sum);
status[1]=zout; // zero flag
status[2]=sum[31];      // negative flag
end
endmodule

alu32_tb.v
`timescale 1ns / 1ps

module alu32_tb;

    // Parameters
    parameter PERIOD = 10; // Time period for clock (in ns)

    // Inputs
    reg [31:0] a;
    reg [31:0] b;
    reg [2:0] gin;

    // Outputs
    wire [31:0] sum;
    wire zout;
    wire [2:0] status;

    // Instantiate the unit under test (UUT)
    alu32 uut (
        .sum(sum),
        .a(a),
        .b(b),
        .zout(zout),
        .gin(gin),
        .status(status)
    );

    // Clock generation
    reg clk;
    always #((PERIOD / 2)) clk = ~clk;

    // Test stimulus
    initial begin
        $monitor("Time=%0t, a=%h, b=%h, gin=%b, sum=%h, zout=%b, status=%b", $time, a, b, gin, sum, zout, status);
        $dumpfile("alu32_tb.vcd");  // Specify the VCD file name
        $dumpvars(0, alu32_tb);      // Dump variables for the entire hierarchy

        // Test case 1: ADD (ALU control line = 010)
        a = 32'h00000001;
        b = 32'h00000002;
        gin = 3'b010;
        #10;

        // Test case 2: SUB (ALU control line = 110)
        a = 32'h00000003;
        b = 32'h00000002;
        gin = 3'b110;
        #10;

        // Test case 3: SLT (ALU control line = 111)
        a = 32'h00000001;
        b = 32'h00000002;
        gin = 3'b111;
        #10;

        // Test case 4: AND (ALU control line = 000)
        a = 32'hFFFFFFFF;
        b = 32'h0000000F;
        gin = 3'b000;
        #10;

        // Test case 5: OR (ALU control line = 001)
        a = 32'hFFFFFFFF;
        b = 32'h00000000;
        gin = 3'b001;
        #10;

        // Test case 6: Zero Flag (Z)
        a = 32'h00000000;
        b = 32'h00000000;
        gin = 3'b010;
        #10;

        // Test case 7: Negative Flag (N)
        a = 32'hFFFFFFFF;
        b = 32'h00000001;
        gin = 3'b010;
        #10;

        // Test case 8: Overflow Flag (V)
        a = 32'h7FFFFFFF;
        b = 32'h00000001;
        gin = 3'b010;
        #10;

        // Add more test cases as needed
        // ...

        // Terminate simulation
        $finish;
    end

endmodule

alu32_tb.vcd
$date
	Wed May 22 16:17:09 2024
$end
$version
	Icarus Verilog
$end
$timescale
	1ps
$end
$scope module alu32_tb $end
$var wire 1 ! zout $end
$var wire 32 " sum [31:0] $end
$var wire 3 # status [2:0] $end
$var parameter 32 $ PERIOD $end
$var reg 32 % a [31:0] $end
$var reg 32 & b [31:0] $end
$var reg 1 ' clk $end
$var reg 3 ( gin [2:0] $end
$scope module uut $end
$var wire 32 ) a [31:0] $end
$var wire 32 * b [31:0] $end
$var wire 3 + gin [2:0] $end
$var reg 32 , less [31:0] $end
$var reg 3 - status [2:0] $end
$var reg 32 . sum [31:0] $end
$var reg 1 ! zout $end
$upscope $end
$upscope $end
$enddefinitions $end
$comment Show the parameter values. $end
$dumpall
b1010 $
$end
#0
$dumpvars
b11 .
b0 -
bx ,
b10 +
b10 *
b1 )
b10 (
x'
b10 &
b1 %
b0 #
b11 "
0!
$end
#10000
b1 "
b1 .
b110 (
b110 +
b11 %
b11 )
#20000
b11111111111111111111111111111111 ,
b111 (
b111 +
b1 %
b1 )
#30000
b1111 "
b1111 .
b0 (
b0 +
b1111 &
b1111 *
b11111111111111111111111111111111 %
b11111111111111111111111111111111 )
#40000
b100 #
b100 -
b11111111111111111111111111111111 "
b11111111111111111111111111111111 .
b1 (
b1 +
b0 &
b0 *
#50000
1!
b0 "
b0 .
b10 #
b10 -
b10 (
b10 +
b0 %
b0 )
#60000
b10 #
b10 -
b1 &
b1 *
b11111111111111111111111111111111 %
b11111111111111111111111111111111 )
#70000
0!
b10000000000000000000000000000000 "
b10000000000000000000000000000000 .
b101 #
b101 -
b1111111111111111111111111111111 %
b1111111111111111111111111111111 )
